[
  {
    "trend_arrow": "NOT_COMPUTABLE", 
    "display_time": "2017-04-27T15:14:27-07:00", 
    "noise": 1, 
    "system_time": "2017-04-27T21:03:46-07:00", 
    "direction": "NOT COMPUTABLE", 
    "sgv": 74, 
    "dateString": "2017-04-27T15:14:27-07:00", 
    "device": "openaps://indy-ex2/cgm", 
    "unfiltered": 92704, 
    "rssi": 181, 
    "date": 1493331267000, 
    "filtered": 104224, 
    "type": "sgv", 
    "glucose": 74
  }, 
  {
    "trend_arrow": "FLAT", 
    "display_time": "2017-04-27T21:04:27-07:00", 
    "noise": 1, 
    "system_time": "2017-04-28T02:53:45-07:00", 
    "direction": "Flat", 
    "sgv": 63, 
    "dateString": "2017-04-27T21:04:27-07:00", 
    "date": 1493352267000, 
    "unfiltered": 85040, 
    "filtered": 82928, 
    "device": "openaps://indy-ex2/cgm", 
    "rssi": 439, 
    "type": "sgv", 
    "glucose": 63
  }, 
  {
    "trend_arrow": "FLAT", 
    "display_time": "2017-04-27T20:59:26-07:00", 
    "noise": 1, 
    "system_time": "2017-04-28T02:48:44-07:00", 
    "direction": "Flat", 
    "sgv": 61, 
    "dateString": "2017-04-27T20:59:26-07:00", 
    "date": 1493351966000, 
    "unfiltered": 83680, 
    "filtered": 83680, 
    "device": "openaps://indy-ex2/cgm", 
    "rssi": 196, 
    "type": "sgv", 
    "glucose": 61
  }
]