[
  {
    "trend_arrow": "45_DOWN", 
    "display_time": "2017-04-22T12:39:12-07:00", 
    "noise": 1, 
    "system_time": "2017-04-22T20:39:09-07:00", 
    "direction": "FortyFiveDown", 
    "sgv": 78, 
    "dateString": "2017-04-22T12:39:12-07:00", 
    "date": 1492889952000, 
    "unfiltered": 92784, 
    "filtered": 104256, 
    "device": "openaps://indy-ex2/cgm", 
    "rssi": 183, 
    "type": "sgv", 
    "glucose": 78
  }, 
  {
    "trend_arrow": "45_DOWN", 
    "display_time": "2017-04-22T12:34:13-07:00", 
    "noise": 1, 
    "system_time": "2017-04-22T20:34:09-07:00", 
    "direction": "FortyFiveDown", 
    "sgv": 87, 
    "dateString": "2017-04-22T12:34:13-07:00", 
    "date": 1492889653000, 
    "unfiltered": 100304, 
    "filtered": 110160, 
    "device": "openaps://indy-ex2/cgm", 
    "rssi": 431, 
    "type": "sgv", 
    "glucose": 87
  }
]