[
  {
    "trend_arrow": "FLAT", 
    "display_time": "2017-03-16T00:46:28-07:00", 
    "noise": 1, 
    "system_time": "2017-03-16T06:36:43-07:00", 
    "direction": "Flat", 
    "sgv": 61, 
    "dateString": "2017-03-16T00:46:28-07:00", 
    "date": 1489650388000, 
    "unfiltered": 82784, 
    "filtered": 81472, 
    "device": "openaps://indy-ex2/cgm", 
    "rssi": 188, 
    "type": "sgv", 
    "glucose": 61
  }, 
  {
    "trend_arrow": "FLAT", 
    "display_time": "2017-03-16T00:41:29-07:00", 
    "noise": 1, 
    "system_time": "2017-03-16T06:31:44-07:00", 
    "direction": "Flat", 
    "sgv": 61, 
    "dateString": "2017-03-16T00:41:29-07:00", 
    "date": 1489650089000, 
    "unfiltered": 82384, 
    "filtered": 82832, 
    "device": "openaps://indy-ex2/cgm", 
    "rssi": 443, 
    "type": "sgv", 
    "glucose": 61
  }
]