[
  {
    "trend_arrow": "45_DOWN", 
    "display_time": "2017-03-11T13:26:44-08:00", 
    "noise": 1, 
    "system_time": "2017-03-11T20:17:01-08:00", 
    "direction": "FortyFiveDown", 
    "sgv": 102, 
    "dateString": "2017-03-11T13:26:44-08:00", 
    "date": 1489267604000, 
    "unfiltered": 114128, 
    "filtered": 121680, 
    "device": "openaps://indy-ex2/cgm", 
    "rssi": 164, 
    "type": "sgv", 
    "glucose": 102
  }, 
  {
    "trend_arrow": "45_DOWN", 
    "display_time": "2017-03-11T13:21:44-08:00", 
    "noise": 1, 
    "system_time": "2017-03-11T20:12:01-08:00", 
    "direction": "FortyFiveDown", 
    "sgv": 108, 
    "dateString": "2017-03-11T13:21:44-08:00", 
    "date": 1489267304000, 
    "unfiltered": 119728, 
    "filtered": 126656, 
    "device": "openaps://indy-ex2/cgm", 
    "rssi": 166, 
    "type": "sgv", 
    "glucose": 108
  }
]