[
  {
    "trend_arrow": "45_UP", 
    "display_time": "2017-04-06T17:40:31-07:00", 
    "noise": 1, 
    "system_time": "2017-04-07T01:40:27-07:00", 
    "direction": "FortyFiveUp", 
    "sgv": 104, 
    "dateString": "2017-04-06T17:40:31-07:00", 
    "date": 1491525631000, 
    "unfiltered": 124624, 
    "filtered": 119136, 
    "device": "openaps://indy-ex2/cgm", 
    "rssi": 194, 
    "type": "sgv", 
    "glucose": 104
  }, 
  {
    "trend_arrow": "45_UP", 
    "display_time": "2017-04-06T17:35:31-07:00", 
    "noise": 1, 
    "system_time": "2017-04-07T01:35:27-07:00", 
    "direction": "FortyFiveUp", 
    "sgv": 100, 
    "dateString": "2017-04-06T17:35:31-07:00", 
    "date": 1491525331000, 
    "unfiltered": 121184, 
    "filtered": 111264, 
    "device": "openaps://indy-ex2/cgm", 
    "rssi": 196, 
    "type": "sgv", 
    "glucose": 100
  }
]