[
  {
    "trend_arrow": "FLAT", 
    "display_time": "2017-03-14T15:31:33-07:00", 
    "noise": 1, 
    "system_time": "2017-03-14T21:21:49-07:00", 
    "direction": "Flat", 
    "sgv": 74, 
    "dateString": "2017-03-14T15:31:33-07:00", 
    "date": 1489530693000, 
    "unfiltered": 94480, 
    "filtered": 96432, 
    "device": "openaps://indy-ex2/cgm", 
    "rssi": 188, 
    "type": "sgv", 
    "glucose": 74
  }, 
  {
    "trend_arrow": "NOT_COMPUTABLE", 
    "display_time": "2017-03-14T15:26:33-07:00", 
    "noise": 1, 
    "system_time": "2017-03-14T21:16:49-07:00", 
    "direction": "NOT COMPUTABLE", 
    "sgv": 74, 
    "dateString": "2017-03-14T15:26:33-07:00", 
    "date": 1489530393000, 
    "unfiltered": 94384, 
    "filtered": 100464, 
    "device": "openaps://indy-ex2/cgm", 
    "rssi": 172, 
    "type": "sgv", 
    "glucose": 74
  }
]