[
  {
    "trend_arrow": "FLAT", 
    "display_time": "2017-04-12T16:34:36-07:00", 
    "noise": 1, 
    "system_time": "2017-04-12T22:24:11-07:00", 
    "direction": "Flat", 
    "sgv": 70, 
    "dateString": "2017-04-12T16:34:36-07:00", 
    "date": 1492040076000, 
    "unfiltered": 89424, 
    "filtered": 84416, 
    "device": "openaps://indy-ex2/cgm", 
    "rssi": 196, 
    "type": "sgv", 
    "glucose": 70
  }, 
  {
    "trend_arrow": "FLAT", 
    "display_time": "2017-04-12T16:29:37-07:00", 
    "noise": 1, 
    "system_time": "2017-04-12T22:19:11-07:00", 
    "direction": "Flat", 
    "sgv": 66, 
    "dateString": "2017-04-12T16:29:37-07:00", 
    "date": 1492039777000, 
    "unfiltered": 86352, 
    "filtered": 80544, 
    "device": "openaps://indy-ex2/cgm", 
    "rssi": 418, 
    "type": "sgv", 
    "glucose": 66
  }
]