[
  {
    "trend_arrow": "FLAT", 
    "display_time": "2017-04-22T18:09:12-07:00", 
    "noise": 1, 
    "direction": "Flat", 
    "system_time": "2017-04-23T02:09:08-07:00", 
    "sgv": 83, 
    "dateString": "2017-04-22T18:09:12-07:00", 
    "device": "openaps://indy-ex2/cgm", 
    "unfiltered": 97216, 
    "rssi": 191, 
    "date": 1492909752000.0, 
    "filtered": 101184, 
    "type": "sgv", 
    "glucose": 83
  }, 
  {
    "trend_arrow": "FLAT", 
    "display_time": "2017-04-22T18:04:12-07:00", 
    "noise": 1, 
    "direction": "Flat", 
    "system_time": "2017-04-23T02:04:08-07:00", 
    "sgv": 87, 
    "dateString": "2017-04-22T18:04:12-07:00", 
    "device": "openaps://indy-ex2/cgm", 
    "unfiltered": 99968, 
    "rssi": 190, 
    "date": 1492909452000.0, 
    "filtered": 103920, 
    "type": "sgv", 
    "glucose": 87
  }, 
  {
    "trend_arrow": "FLAT", 
    "display_time": "2017-04-22T17:59:12-07:00", 
    "noise": 1, 
    "direction": "Flat", 
    "system_time": "2017-04-23T01:59:08-07:00", 
    "sgv": 91, 
    "dateString": "2017-04-22T17:59:12-07:00", 
    "device": "openaps://indy-ex2/cgm", 
    "unfiltered": 102848, 
    "rssi": 196, 
    "date": 1492909152000.0, 
    "filtered": 107040, 
    "type": "sgv", 
    "glucose": 91
  }, 
  {
    "trend_arrow": "FLAT", 
    "display_time": "2017-04-22T17:54:12-07:00", 
    "noise": 1, 
    "direction": "Flat", 
    "system_time": "2017-04-23T01:54:08-07:00", 
    "sgv": 94, 
    "dateString": "2017-04-22T17:54:12-07:00", 
    "device": "openaps://indy-ex2/cgm", 
    "unfiltered": 105296, 
    "rssi": 192, 
    "date": 1492908852000.0, 
    "filtered": 110320, 
    "type": "sgv", 
    "glucose": 94
  }, 
  {
    "trend_arrow": "FLAT", 
    "display_time": "2017-04-22T17:49:12-07:00", 
    "noise": 1, 
    "direction": "Flat", 
    "system_time": "2017-04-23T01:49:08-07:00", 
    "sgv": 97, 
    "dateString": "2017-04-22T17:49:12-07:00", 
    "device": "openaps://indy-ex2/cgm", 
    "unfiltered": 107744, 
    "rssi": 197, 
    "date": 1492908552000.0, 
    "filtered": 113360, 
    "type": "sgv", 
    "glucose": 97
  }, 
  {
    "trend_arrow": "FLAT", 
    "display_time": "2017-04-22T17:44:12-07:00", 
    "noise": 1, 
    "direction": "Flat", 
    "system_time": "2017-04-23T01:44:08-07:00", 
    "sgv": 103, 
    "dateString": "2017-04-22T17:44:12-07:00", 
    "device": "openaps://indy-ex2/cgm", 
    "unfiltered": 112192, 
    "rssi": 186, 
    "date": 1492908252000.0, 
    "filtered": 115792, 
    "type": "sgv", 
    "glucose": 103
  }
]