[
  {
    "trend_arrow": "FLAT", 
    "system_time": "2017-04-07T09:50:26", 
    "noise": 1, 
    "direction": "Flat", 
    "sgv": 101, 
    "display_time": "2017-04-07T01:50:30", 
    "date": 1491555030000.0, 
    "dateString": "2017-04-07T01:50:30", 
    "unfiltered": 122080, 
    "filtered": 126576, 
    "device": "openaps://indy-ex2/cgm", 
    "rssi": 193, 
    "type": "sgv", 
    "glucose": 101
  }, 
  {
    "trend_arrow": "FLAT", 
    "system_time": "2017-04-07T09:45:26", 
    "noise": 1, 
    "direction": "Flat", 
    "sgv": 104, 
    "display_time": "2017-04-07T01:45:30", 
    "date": 1491554730000.0, 
    "dateString": "2017-04-07T01:45:30", 
    "unfiltered": 124704, 
    "filtered": 129120, 
    "device": "openaps://indy-ex2/cgm", 
    "rssi": 193, 
    "type": "sgv", 
    "glucose": 104
  }, 
  {
    "trend_arrow": "FLAT", 
    "system_time": "2017-04-07T09:40:26", 
    "noise": 1, 
    "direction": "Flat", 
    "sgv": 107, 
    "display_time": "2017-04-07T01:40:30", 
    "date": 1491554430000.0, 
    "dateString": "2017-04-07T01:40:30", 
    "unfiltered": 127888, 
    "filtered": 131136, 
    "device": "openaps://indy-ex2/cgm", 
    "rssi": 196, 
    "type": "sgv", 
    "glucose": 107
  }, 
  {
    "trend_arrow": "FLAT", 
    "system_time": "2017-04-07T09:35:26", 
    "noise": 1, 
    "direction": "Flat", 
    "sgv": 109, 
    "display_time": "2017-04-07T01:35:30", 
    "date": 1491554130000.0, 
    "dateString": "2017-04-07T01:35:30", 
    "unfiltered": 130304, 
    "filtered": 132576, 
    "device": "openaps://indy-ex2/cgm", 
    "rssi": 196, 
    "type": "sgv", 
    "glucose": 109
  }, 
  {
    "trend_arrow": "FLAT", 
    "system_time": "2017-04-07T09:30:26", 
    "noise": 1, 
    "direction": "Flat", 
    "sgv": 111, 
    "display_time": "2017-04-07T01:30:30", 
    "date": 1491553830000.0, 
    "dateString": "2017-04-07T01:30:30", 
    "unfiltered": 131904, 
    "filtered": 133408, 
    "device": "openaps://indy-ex2/cgm", 
    "rssi": 196, 
    "type": "sgv", 
    "glucose": 111
  }, 
  {
    "trend_arrow": "FLAT", 
    "system_time": "2017-04-07T09:25:26", 
    "noise": 1, 
    "direction": "Flat", 
    "sgv": 112, 
    "display_time": "2017-04-07T01:25:30", 
    "date": 1491553530000.0, 
    "dateString": "2017-04-07T01:25:30", 
    "unfiltered": 132832, 
    "filtered": 133600, 
    "device": "openaps://indy-ex2/cgm", 
    "rssi": 196, 
    "type": "sgv", 
    "glucose": 112
  }
]