[
  {
    "trend_arrow": "FLAT", 
    "display_time": "2017-04-28T17:19:22-07:00", 
    "noise": 1, 
    "system_time": "2017-04-28T23:08:41-07:00", 
    "direction": "Flat", 
    "sgv": 117, 
    "dateString": "2017-04-28T17:19:22-07:00", 
    "device": "openaps://indy-ex2/cgm", 
    "unfiltered": 120416, 
    "rssi": 170, 
    "date": 1493425162000, 
    "filtered": 116912, 
    "type": "sgv", 
    "glucose": 117
  }, 
  {
    "trend_arrow": "FLAT", 
    "display_time": "2017-04-28T17:14:22-07:00", 
    "noise": 1, 
    "system_time": "2017-04-28T23:03:41-07:00", 
    "direction": "Flat", 
    "sgv": 114, 
    "dateString": "2017-04-28T17:14:22-07:00", 
    "device": "openaps://indy-ex2/cgm", 
    "unfiltered": 118608, 
    "rssi": 185, 
    "date": 1493424862000, 
    "filtered": 113424, 
    "type": "sgv", 
    "glucose": 114
  }
]