[
  {
    "trend_arrow": "FLAT", 
    "display_time": "2017-04-20T00:04:19-07:00", 
    "noise": 1, 
    "direction": "Flat", 
    "system_time": "2017-04-20T08:04:15-07:00", 
    "sgv": 152, 
    "dateString": "2017-04-20T00:04:19-07:00", 
    "device": "openaps://indy-ex2/cgm", 
    "unfiltered": 154272, 
    "rssi": 192, 
    "date": 1492671859000.0, 
    "filtered": 159104, 
    "type": "sgv", 
    "glucose": 152
  }, 
  {
    "trend_arrow": "FLAT", 
    "display_time": "2017-04-19T23:59:19-07:00", 
    "noise": 1, 
    "direction": "Flat", 
    "system_time": "2017-04-20T07:59:15-07:00", 
    "sgv": 155, 
    "dateString": "2017-04-19T23:59:19-07:00", 
    "device": "openaps://indy-ex2/cgm", 
    "unfiltered": 157024, 
    "rssi": 192, 
    "date": 1492671559000.0, 
    "filtered": 163520, 
    "type": "sgv", 
    "glucose": 155
  }, 
  {
    "trend_arrow": "FLAT", 
    "display_time": "2017-04-19T23:54:19-07:00", 
    "noise": 1, 
    "direction": "Flat", 
    "system_time": "2017-04-20T07:54:15-07:00", 
    "sgv": 159, 
    "dateString": "2017-04-19T23:54:19-07:00", 
    "device": "openaps://indy-ex2/cgm", 
    "unfiltered": 160256, 
    "rssi": 192, 
    "date": 1492671259000.0, 
    "filtered": 167744, 
    "type": "sgv", 
    "glucose": 159
  }, 
  {
    "trend_arrow": "FLAT", 
    "display_time": "2017-04-19T23:49:19-07:00", 
    "noise": 1, 
    "direction": "Flat", 
    "system_time": "2017-04-20T07:49:15-07:00", 
    "sgv": 165, 
    "dateString": "2017-04-19T23:49:19-07:00", 
    "device": "openaps://indy-ex2/cgm", 
    "unfiltered": 165216, 
    "rssi": 192, 
    "date": 1492670959000.0, 
    "filtered": 170944, 
    "type": "sgv", 
    "glucose": 165
  }, 
  {
    "trend_arrow": "FLAT", 
    "display_time": "2017-04-19T23:44:19-07:00", 
    "noise": 1, 
    "direction": "Flat", 
    "system_time": "2017-04-20T07:44:15-07:00", 
    "sgv": 170, 
    "dateString": "2017-04-19T23:44:19-07:00", 
    "device": "openaps://indy-ex2/cgm", 
    "unfiltered": 169536, 
    "rssi": 186, 
    "date": 1492670659000.0, 
    "filtered": 172768, 
    "type": "sgv", 
    "glucose": 170
  }, 
  {
    "trend_arrow": "FLAT", 
    "display_time": "2017-04-19T23:39:19-07:00", 
    "noise": 1, 
    "direction": "Flat", 
    "system_time": "2017-04-20T07:39:15-07:00", 
    "sgv": 173, 
    "dateString": "2017-04-19T23:39:19-07:00", 
    "device": "openaps://indy-ex2/cgm", 
    "unfiltered": 171968, 
    "rssi": 185, 
    "date": 1492670359000.0, 
    "filtered": 173536, 
    "type": "sgv", 
    "glucose": 173
  }
]