[
  {
    "trend_arrow": "45_UP", 
    "display_time": "2017-03-19T08:50:37-07:00", 
    "noise": 1, 
    "system_time": "2017-03-19T14:40:45-07:00", 
    "direction": "FortyFiveUp", 
    "sgv": 127, 
    "dateString": "2017-03-19T08:50:37-07:00", 
    "device": "openaps://indy-ex2/cgm", 
    "unfiltered": 128688, 
    "rssi": 196, 
    "date": 1489938637000, 
    "filtered": 124416, 
    "type": "sgv", 
    "glucose": 127
  }, 
  {
    "trend_arrow": "45_UP", 
    "display_time": "2017-03-19T08:45:37-07:00", 
    "noise": 1, 
    "system_time": "2017-03-19T14:35:45-07:00", 
    "direction": "FortyFiveUp", 
    "sgv": 124, 
    "dateString": "2017-03-19T08:45:37-07:00", 
    "device": "openaps://indy-ex2/cgm", 
    "unfiltered": 126672, 
    "rssi": 198, 
    "date": 1489938337000, 
    "filtered": 117488, 
    "type": "sgv", 
    "glucose": 124
  }
]