[
  {
    "trend_arrow": "FLAT", 
    "display_time": "2017-05-06T06:49:08-07:00", 
    "noise": 1, 
    "system_time": "2017-05-06T14:49:03-07:00", 
    "direction": "Flat", 
    "sgv": 101, 
    "dateString": "2017-05-06T06:49:08-07:00", 
    "device": "openaps://indy-ex2/cgm", 
    "unfiltered": 117744, 
    "rssi": 183, 
    "date": 1494078548000, 
    "filtered": 119232, 
    "type": "sgv", 
    "glucose": 101
  }, 
  {
    "trend_arrow": "FLAT", 
    "display_time": "2017-05-06T06:44:08-07:00", 
    "noise": 1, 
    "system_time": "2017-05-06T14:44:04-07:00", 
    "direction": "Flat", 
    "sgv": 102, 
    "dateString": "2017-05-06T06:44:08-07:00", 
    "device": "openaps://indy-ex2/cgm", 
    "unfiltered": 118704, 
    "rssi": 443, 
    "date": 1494078248000, 
    "filtered": 120352, 
    "type": "sgv", 
    "glucose": 102
  }
]