[
  {
    "trend_arrow": "FLAT", 
    "display_time": "2017-03-31T04:15:49-07:00", 
    "noise": 1, 
    "system_time": "2017-03-31T12:15:46-07:00", 
    "direction": "Flat", 
    "sgv": 138, 
    "dateString": "2017-03-31T04:15:49-07:00", 
    "device": "openaps://indy-ex2/cgm", 
    "unfiltered": 133152, 
    "rssi": 188, 
    "date": 1490958949000, 
    "filtered": 133696, 
    "type": "sgv", 
    "glucose": 138
  }, 
  {
    "trend_arrow": "FLAT", 
    "display_time": "2017-03-31T04:10:50-07:00", 
    "noise": 1, 
    "system_time": "2017-03-31T12:10:46-07:00", 
    "direction": "Flat", 
    "sgv": 138, 
    "dateString": "2017-03-31T04:10:50-07:00", 
    "device": "openaps://indy-ex2/cgm", 
    "unfiltered": 132928, 
    "rssi": 188, 
    "date": 1490958650000, 
    "filtered": 135328, 
    "type": "sgv", 
    "glucose": 138
  }
]