[
  {
    "trend_arrow": "NOT_COMPUTABLE", 
    "display_time": "2017-03-18T17:10:39-07:00", 
    "noise": 3, 
    "system_time": "2017-03-18T23:00:47-07:00", 
    "direction": "NOT COMPUTABLE", 
    "sgv": 177, 
    "dateString": "2017-03-18T17:10:39-07:00", 
    "device": "openaps://indy-ex2/cgm", 
    "unfiltered": 177024, 
    "rssi": 197, 
    "date": 1489882239000, 
    "filtered": 168960, 
    "type": "sgv", 
    "glucose": 177
  }, 
  {
    "trend_arrow": "NOT_COMPUTABLE", 
    "display_time": "2017-03-18T17:05:39-07:00", 
    "noise": 3, 
    "system_time": "2017-03-18T22:55:48-07:00", 
    "direction": "NOT COMPUTABLE", 
    "sgv": 159, 
    "dateString": "2017-03-18T17:05:39-07:00", 
    "device": "openaps://indy-ex2/cgm", 
    "unfiltered": 173248, 
    "rssi": 193, 
    "date": 1489881939000, 
    "filtered": 155904, 
    "type": "sgv", 
    "glucose": 159
  }
]