[
  {
    "trend_arrow": "FLAT", 
    "display_time": "2017-04-02T05:25:43-07:00", 
    "noise": 1, 
    "system_time": "2017-04-02T13:25:40-07:00", 
    "direction": "Flat", 
    "sgv": 129, 
    "dateString": "2017-04-02T05:25:43-07:00", 
    "device": "openaps://indy-ex2/cgm", 
    "unfiltered": 126432, 
    "rssi": 185, 
    "date": 1491135943000, 
    "filtered": 129632, 
    "type": "sgv", 
    "glucose": 129
  }, 
  {
    "trend_arrow": "FLAT", 
    "display_time": "2017-04-02T05:20:43-07:00", 
    "noise": 1, 
    "system_time": "2017-04-02T13:20:40-07:00", 
    "direction": "Flat", 
    "sgv": 133, 
    "dateString": "2017-04-02T05:20:43-07:00", 
    "device": "openaps://indy-ex2/cgm", 
    "unfiltered": 128992, 
    "rssi": 185, 
    "date": 1491135643000, 
    "filtered": 130960, 
    "type": "sgv", 
    "glucose": 133
  }
]