[
  {
    "trend_arrow": "45_DOWN", 
    "display_time": "2017-04-25T16:29:35-07:00", 
    "noise": 1, 
    "system_time": "2017-04-25T22:18:54-07:00", 
    "direction": "FortyFiveDown", 
    "sgv": 76, 
    "dateString": "2017-04-25T16:29:35-07:00", 
    "device": "openaps://indy-ex2/cgm", 
    "unfiltered": 91680, 
    "rssi": 178, 
    "date": 1493162975000, 
    "filtered": 93632, 
    "type": "sgv", 
    "glucose": 76
  }, 
  {
    "trend_arrow": "45_DOWN", 
    "display_time": "2017-04-25T16:24:36-07:00", 
    "noise": 1, 
    "system_time": "2017-04-25T22:13:54-07:00", 
    "direction": "FortyFiveDown", 
    "sgv": 75, 
    "dateString": "2017-04-25T16:24:36-07:00", 
    "device": "openaps://indy-ex2/cgm", 
    "unfiltered": 91312, 
    "rssi": 445, 
    "date": 1493162676000, 
    "filtered": 98912, 
    "type": "sgv", 
    "glucose": 75
  }
]