[
  {
    "trend_arrow": "FLAT", 
    "display_time": "2017-04-24T01:44:42-07:00", 
    "noise": 1, 
    "direction": "Flat", 
    "system_time": "2017-04-24T07:34:00-07:00", 
    "sgv": 69, 
    "dateString": "2017-04-24T01:44:42-07:00", 
    "device": "openaps://indy-ex2/cgm", 
    "unfiltered": 81216, 
    "rssi": 194, 
    "date": 1493023482000.0, 
    "filtered": 83760, 
    "type": "sgv", 
    "glucose": 69
  }, 
  {
    "trend_arrow": "NOT_COMPUTABLE", 
    "display_time": "2017-04-24T01:39:42-07:00", 
    "noise": 3, 
    "direction": "NOT COMPUTABLE", 
    "system_time": "2017-04-24T07:29:00-07:00", 
    "sgv": 77, 
    "dateString": "2017-04-24T01:39:42-07:00", 
    "device": "openaps://indy-ex2/cgm", 
    "unfiltered": 81952, 
    "rssi": 195, 
    "date": 1493023182000.0, 
    "filtered": 86304, 
    "type": "sgv", 
    "glucose": 77
  }, 
  {
    "trend_arrow": "NOT_COMPUTABLE", 
    "display_time": "2017-04-24T01:34:42-07:00", 
    "noise": 3, 
    "direction": "NOT COMPUTABLE", 
    "system_time": "2017-04-24T07:24:00-07:00", 
    "sgv": 76, 
    "dateString": "2017-04-24T01:34:42-07:00", 
    "device": "openaps://indy-ex2/cgm", 
    "unfiltered": 83024, 
    "rssi": 193, 
    "date": 1493022882000.0, 
    "filtered": 85760, 
    "type": "sgv", 
    "glucose": 76
  }, 
  {
    "trend_arrow": "NOT_COMPUTABLE", 
    "display_time": "2017-04-24T01:29:42-07:00", 
    "noise": 3, 
    "direction": "NOT COMPUTABLE", 
    "system_time": "2017-04-24T07:19:00-07:00", 
    "sgv": 66, 
    "dateString": "2017-04-24T01:29:42-07:00", 
    "device": "openaps://indy-ex2/cgm", 
    "unfiltered": 83808, 
    "rssi": 193, 
    "date": 1493022582000.0, 
    "filtered": 79344, 
    "type": "sgv", 
    "glucose": 66
  }, 
  {
    "trend_arrow": "NOT_COMPUTABLE", 
    "display_time": "2017-04-24T01:24:42-07:00", 
    "noise": 3, 
    "direction": "NOT COMPUTABLE", 
    "system_time": "2017-04-24T07:14:00-07:00", 
    "sgv": 51, 
    "dateString": "2017-04-24T01:24:42-07:00", 
    "device": "openaps://indy-ex2/cgm", 
    "unfiltered": 81968, 
    "rssi": 192, 
    "date": 1493022282000.0, 
    "filtered": 70000, 
    "type": "sgv", 
    "glucose": 51
  }, 
  {
    "trend_arrow": "NOT_COMPUTABLE", 
    "display_time": "2017-04-24T01:19:42-07:00", 
    "noise": 3, 
    "direction": "NOT COMPUTABLE", 
    "system_time": "2017-04-24T07:09:00-07:00", 
    "sgv": 43, 
    "dateString": "2017-04-24T01:19:42-07:00", 
    "device": "openaps://indy-ex2/cgm", 
    "unfiltered": 85232, 
    "rssi": 192, 
    "date": 1493021982000.0, 
    "filtered": 64832, 
    "type": "sgv", 
    "glucose": 43
  }
]