[
  {
    "trend_arrow": "45_UP", 
    "display_time": "2017-04-13T13:04:33-07:00", 
    "noise": 1, 
    "direction": "FortyFiveUp", 
    "system_time": "2017-04-13T18:54:08-07:00", 
    "sgv": 103, 
    "dateString": "2017-04-13T13:04:33-07:00", 
    "device": "openaps://indy-ex2/cgm", 
    "unfiltered": 118496, 
    "rssi": 200, 
    "date": 1492113873000.0, 
    "filtered": 102752, 
    "type": "sgv", 
    "glucose": 103
  }, 
  {
    "trend_arrow": "FLAT", 
    "display_time": "2017-04-13T12:59:33-07:00", 
    "noise": 1, 
    "direction": "Flat", 
    "system_time": "2017-04-13T18:49:08-07:00", 
    "sgv": 92, 
    "dateString": "2017-04-13T12:59:33-07:00", 
    "device": "openaps://indy-ex2/cgm", 
    "unfiltered": 109056, 
    "rssi": 199, 
    "date": 1492113573000.0, 
    "filtered": 97984, 
    "type": "sgv", 
    "glucose": 92
  }, 
  {
    "trend_arrow": "FLAT", 
    "display_time": "2017-04-13T12:54:33-07:00", 
    "noise": 1, 
    "direction": "Flat", 
    "system_time": "2017-04-13T18:44:08-07:00", 
    "sgv": 81, 
    "dateString": "2017-04-13T12:54:33-07:00", 
    "device": "openaps://indy-ex2/cgm", 
    "unfiltered": 99984, 
    "rssi": 196, 
    "date": 1492113273000.0, 
    "filtered": 97312, 
    "type": "sgv", 
    "glucose": 81
  }, 
  {
    "trend_arrow": "FLAT", 
    "display_time": "2017-04-13T12:49:33-07:00", 
    "noise": 1, 
    "direction": "Flat", 
    "system_time": "2017-04-13T18:39:08-07:00", 
    "sgv": 75, 
    "dateString": "2017-04-13T12:49:33-07:00", 
    "device": "openaps://indy-ex2/cgm", 
    "unfiltered": 95216, 
    "rssi": 198, 
    "date": 1492112973000.0, 
    "filtered": 98544, 
    "type": "sgv", 
    "glucose": 75
  }, 
  {
    "trend_arrow": "FLAT", 
    "display_time": "2017-04-13T12:44:33-07:00", 
    "noise": 1, 
    "direction": "Flat", 
    "system_time": "2017-04-13T18:34:08-07:00", 
    "sgv": 76, 
    "dateString": "2017-04-13T12:44:33-07:00", 
    "device": "openaps://indy-ex2/cgm", 
    "unfiltered": 96032, 
    "rssi": 198, 
    "date": 1492112673000.0, 
    "filtered": 98752, 
    "type": "sgv", 
    "glucose": 76
  }, 
  {
    "trend_arrow": "NOT_COMPUTABLE", 
    "display_time": "2017-04-13T12:39:33-07:00", 
    "noise": 1, 
    "direction": "NOT COMPUTABLE", 
    "system_time": "2017-04-13T18:29:08-07:00", 
    "sgv": 79, 
    "dateString": "2017-04-13T12:39:33-07:00", 
    "device": "openaps://indy-ex2/cgm", 
    "unfiltered": 98288, 
    "rssi": 183, 
    "date": 1492112373000.0, 
    "filtered": 96720, 
    "type": "sgv", 
    "glucose": 79
  }
]