[
  {
    "trend_arrow": "FLAT", 
    "display_time": "2017-03-15T22:06:28-07:00", 
    "noise": 1, 
    "system_time": "2017-03-16T03:56:44-07:00", 
    "direction": "Flat", 
    "sgv": 126, 
    "dateString": "2017-03-15T22:06:28-07:00", 
    "device": "openaps://indy-ex2/cgm", 
    "unfiltered": 142752, 
    "rssi": 177, 
    "date": 1489640788000, 
    "filtered": 140576, 
    "type": "sgv", 
    "glucose": 126
  }, 
  {
    "trend_arrow": "FLAT", 
    "display_time": "2017-03-15T22:01:28-07:00", 
    "noise": 1, 
    "system_time": "2017-03-16T03:51:44-07:00", 
    "direction": "Flat", 
    "sgv": 124, 
    "dateString": "2017-03-15T22:01:28-07:00", 
    "device": "openaps://indy-ex2/cgm", 
    "unfiltered": 141344, 
    "rssi": 184, 
    "date": 1489640488000, 
    "filtered": 136864, 
    "type": "sgv", 
    "glucose": 124
  }
]