[
  {
    "trend_arrow": "FLAT", 
    "display_time": "2017-04-15T18:19:25-07:00", 
    "noise": 1, 
    "direction": "Flat", 
    "system_time": "2017-04-16T00:08:59-07:00", 
    "sgv": 73, 
    "dateString": "2017-04-15T18:19:25-07:00", 
    "device": "openaps://indy-ex2/cgm", 
    "unfiltered": 86512, 
    "rssi": 205, 
    "date": 1492305565000.0, 
    "filtered": 83968, 
    "type": "sgv", 
    "glucose": 73
  }, 
  {
    "trend_arrow": "FLAT", 
    "display_time": "2017-04-15T18:14:25-07:00", 
    "noise": 1, 
    "direction": "Flat", 
    "system_time": "2017-04-16T00:03:59-07:00", 
    "sgv": 70, 
    "dateString": "2017-04-15T18:14:25-07:00", 
    "device": "openaps://indy-ex2/cgm", 
    "unfiltered": 83840, 
    "rssi": 210, 
    "date": 1492305265000.0, 
    "filtered": 84176, 
    "type": "sgv", 
    "glucose": 70
  }, 
  {
    "trend_arrow": "FLAT", 
    "display_time": "2017-04-15T18:09:25-07:00", 
    "noise": 1, 
    "direction": "Flat", 
    "system_time": "2017-04-15T23:58:59-07:00", 
    "sgv": 70, 
    "dateString": "2017-04-15T18:09:25-07:00", 
    "device": "openaps://indy-ex2/cgm", 
    "unfiltered": 83872, 
    "rssi": 196, 
    "date": 1492304965000.0, 
    "filtered": 85264, 
    "type": "sgv", 
    "glucose": 70
  }, 
  {
    "trend_arrow": "FLAT", 
    "display_time": "2017-04-15T18:04:25-07:00", 
    "noise": 1, 
    "direction": "Flat", 
    "system_time": "2017-04-15T23:53:59-07:00", 
    "sgv": 71, 
    "dateString": "2017-04-15T18:04:25-07:00", 
    "device": "openaps://indy-ex2/cgm", 
    "unfiltered": 84320, 
    "rssi": 203, 
    "date": 1492304665000.0, 
    "filtered": 87232, 
    "type": "sgv", 
    "glucose": 71
  }, 
  {
    "trend_arrow": "45_DOWN", 
    "display_time": "2017-04-15T17:59:25-07:00", 
    "noise": 1, 
    "direction": "FortyFiveDown", 
    "system_time": "2017-04-15T23:48:59-07:00", 
    "sgv": 73, 
    "dateString": "2017-04-15T17:59:25-07:00", 
    "device": "openaps://indy-ex2/cgm", 
    "unfiltered": 86480, 
    "rssi": 196, 
    "date": 1492304365000.0, 
    "filtered": 90720, 
    "type": "sgv", 
    "glucose": 73
  }, 
  {
    "trend_arrow": "45_DOWN", 
    "display_time": "2017-04-15T17:54:25-07:00", 
    "noise": 1, 
    "direction": "FortyFiveDown", 
    "system_time": "2017-04-15T23:43:59-07:00", 
    "sgv": 77, 
    "dateString": "2017-04-15T17:54:25-07:00", 
    "device": "openaps://indy-ex2/cgm", 
    "unfiltered": 89408, 
    "rssi": 179, 
    "date": 1492304065000.0, 
    "filtered": 96704, 
    "type": "sgv", 
    "glucose": 77
  }
]