[
  {
    "trend_arrow": "FLAT", 
    "display_time": "2017-03-14T01:31:36-07:00", 
    "noise": 1, 
    "direction": "Flat", 
    "system_time": "2017-03-14T07:21:51-07:00", 
    "sgv": 121, 
    "dateString": "2017-03-14T01:31:36-07:00", 
    "device": "openaps://indy-ex2/cgm", 
    "unfiltered": 138208, 
    "rssi": 189, 
    "date": 1489480296000.0, 
    "filtered": 132128, 
    "type": "sgv", 
    "glucose": 121
  }, 
  {
    "trend_arrow": "FLAT", 
    "display_time": "2017-03-14T01:26:36-07:00", 
    "noise": 1, 
    "direction": "Flat", 
    "system_time": "2017-03-14T07:16:51-07:00", 
    "sgv": 117, 
    "dateString": "2017-03-14T01:26:36-07:00", 
    "device": "openaps://indy-ex2/cgm", 
    "unfiltered": 133600, 
    "rssi": 185, 
    "date": 1489479996000.0, 
    "filtered": 129568, 
    "type": "sgv", 
    "glucose": 117
  }, 
  {
    "trend_arrow": "FLAT", 
    "display_time": "2017-03-14T01:21:36-07:00", 
    "noise": 1, 
    "direction": "Flat", 
    "system_time": "2017-03-14T07:11:51-07:00", 
    "sgv": 114, 
    "dateString": "2017-03-14T01:21:36-07:00", 
    "device": "openaps://indy-ex2/cgm", 
    "unfiltered": 130688, 
    "rssi": 185, 
    "date": 1489479696000.0, 
    "filtered": 127776, 
    "type": "sgv", 
    "glucose": 114
  }, 
  {
    "trend_arrow": "FLAT", 
    "display_time": "2017-03-14T01:16:36-07:00", 
    "noise": 1, 
    "direction": "Flat", 
    "system_time": "2017-03-14T07:06:52-07:00", 
    "sgv": 111, 
    "dateString": "2017-03-14T01:16:36-07:00", 
    "device": "openaps://indy-ex2/cgm", 
    "unfiltered": 128656, 
    "rssi": 440, 
    "date": 1489479396000.0, 
    "filtered": 126896, 
    "type": "sgv", 
    "glucose": 111
  }, 
  {
    "trend_arrow": "FLAT", 
    "display_time": "2017-03-14T01:11:36-07:00", 
    "noise": 1, 
    "direction": "Flat", 
    "system_time": "2017-03-14T07:01:51-07:00", 
    "sgv": 110, 
    "dateString": "2017-03-14T01:11:36-07:00", 
    "device": "openaps://indy-ex2/cgm", 
    "unfiltered": 127760, 
    "rssi": 185, 
    "date": 1489479096000.0, 
    "filtered": 127456, 
    "type": "sgv", 
    "glucose": 110
  }, 
  {
    "trend_arrow": "FLAT", 
    "display_time": "2017-03-14T01:06:36-07:00", 
    "noise": 1, 
    "direction": "Flat", 
    "system_time": "2017-03-14T06:56:51-07:00", 
    "sgv": 110, 
    "dateString": "2017-03-14T01:06:36-07:00", 
    "device": "openaps://indy-ex2/cgm", 
    "unfiltered": 127344, 
    "rssi": 185, 
    "date": 1489478796000.0, 
    "filtered": 129840, 
    "type": "sgv", 
    "glucose": 110
  }
]