[
  {
    "trend_arrow": "FLAT", 
    "system_time": "2017-03-20T09:35:42", 
    "noise": 1, 
    "direction": "Flat", 
    "sgv": 72, 
    "display_time": "2017-03-20T03:45:34", 
    "date": 1490006734000.0, 
    "dateString": "2017-03-20T03:45:34", 
    "unfiltered": 85280, 
    "filtered": 87760, 
    "device": "openaps://indy-ex2/cgm", 
    "rssi": 196, 
    "type": "sgv", 
    "glucose": 72
  }, 
  {
    "trend_arrow": "FLAT", 
    "system_time": "2017-03-20T09:30:42", 
    "noise": 1, 
    "direction": "Flat", 
    "sgv": 74, 
    "display_time": "2017-03-20T03:40:34", 
    "date": 1490006434000.0, 
    "dateString": "2017-03-20T03:40:34", 
    "unfiltered": 86880, 
    "filtered": 89216, 
    "device": "openaps://indy-ex2/cgm", 
    "rssi": 196, 
    "type": "sgv", 
    "glucose": 74
  }, 
  {
    "trend_arrow": "FLAT", 
    "system_time": "2017-03-20T09:25:42", 
    "noise": 1, 
    "direction": "Flat", 
    "sgv": 76, 
    "display_time": "2017-03-20T03:35:34", 
    "date": 1490006134000.0, 
    "dateString": "2017-03-20T03:35:34", 
    "unfiltered": 88464, 
    "filtered": 90560, 
    "device": "openaps://indy-ex2/cgm", 
    "rssi": 196, 
    "type": "sgv", 
    "glucose": 76
  }, 
  {
    "trend_arrow": "FLAT", 
    "system_time": "2017-03-20T09:20:42", 
    "noise": 1, 
    "direction": "Flat", 
    "sgv": 78, 
    "display_time": "2017-03-20T03:30:34", 
    "date": 1490005834000.0, 
    "dateString": "2017-03-20T03:30:34", 
    "unfiltered": 89904, 
    "filtered": 91776, 
    "device": "openaps://indy-ex2/cgm", 
    "rssi": 196, 
    "type": "sgv", 
    "glucose": 78
  }, 
  {
    "trend_arrow": "FLAT", 
    "system_time": "2017-03-20T09:15:42", 
    "noise": 1, 
    "direction": "Flat", 
    "sgv": 80, 
    "display_time": "2017-03-20T03:25:34", 
    "date": 1490005534000.0, 
    "dateString": "2017-03-20T03:25:34", 
    "unfiltered": 91232, 
    "filtered": 93008, 
    "device": "openaps://indy-ex2/cgm", 
    "rssi": 196, 
    "type": "sgv", 
    "glucose": 80
  }, 
  {
    "trend_arrow": "FLAT", 
    "system_time": "2017-03-20T09:10:42", 
    "noise": 1, 
    "direction": "Flat", 
    "sgv": 81, 
    "display_time": "2017-03-20T03:20:34", 
    "date": 1490005234000.0, 
    "dateString": "2017-03-20T03:20:34", 
    "unfiltered": 92384, 
    "filtered": 94304, 
    "device": "openaps://indy-ex2/cgm", 
    "rssi": 196, 
    "type": "sgv", 
    "glucose": 81
  }
]