[
  {
    "trend_arrow": "45_DOWN", 
    "display_time": "2017-04-03T23:15:38-07:00", 
    "noise": 1, 
    "direction": "FortyFiveDown", 
    "system_time": "2017-04-04T07:15:35-07:00", 
    "sgv": 110, 
    "dateString": "2017-04-03T23:15:38-07:00", 
    "device": "openaps://indy-ex2/cgm", 
    "unfiltered": 126096, 
    "rssi": 185, 
    "date": 1491286538000.0, 
    "filtered": 137568, 
    "type": "sgv", 
    "glucose": 110
  }, 
  {
    "trend_arrow": "FLAT", 
    "display_time": "2017-04-03T23:10:38-07:00", 
    "noise": 1, 
    "direction": "Flat", 
    "system_time": "2017-04-04T07:10:35-07:00", 
    "sgv": 119, 
    "dateString": "2017-04-03T23:10:38-07:00", 
    "device": "openaps://indy-ex2/cgm", 
    "unfiltered": 133888, 
    "rssi": 186, 
    "date": 1491286238000.0, 
    "filtered": 141952, 
    "type": "sgv", 
    "glucose": 119
  }, 
  {
    "trend_arrow": "FLAT", 
    "display_time": "2017-04-03T23:05:39-07:00", 
    "noise": 1, 
    "direction": "Flat", 
    "system_time": "2017-04-04T07:05:36-07:00", 
    "sgv": 126, 
    "dateString": "2017-04-03T23:05:39-07:00", 
    "device": "openaps://indy-ex2/cgm", 
    "unfiltered": 140224, 
    "rssi": 442, 
    "date": 1491285939000.0, 
    "filtered": 143968, 
    "type": "sgv", 
    "glucose": 126
  }, 
  {
    "trend_arrow": "FLAT", 
    "display_time": "2017-04-03T23:00:39-07:00", 
    "noise": 1, 
    "direction": "Flat", 
    "system_time": "2017-04-04T07:00:35-07:00", 
    "sgv": 130, 
    "dateString": "2017-04-03T23:00:39-07:00", 
    "device": "openaps://indy-ex2/cgm", 
    "unfiltered": 143328, 
    "rssi": 185, 
    "date": 1491285639000.0, 
    "filtered": 143936, 
    "type": "sgv", 
    "glucose": 130
  }, 
  {
    "trend_arrow": "FLAT", 
    "display_time": "2017-04-03T22:55:39-07:00", 
    "noise": 1, 
    "direction": "Flat", 
    "system_time": "2017-04-04T06:55:35-07:00", 
    "sgv": 131, 
    "dateString": "2017-04-03T22:55:39-07:00", 
    "device": "openaps://indy-ex2/cgm", 
    "unfiltered": 144224, 
    "rssi": 186, 
    "date": 1491285339000.0, 
    "filtered": 142528, 
    "type": "sgv", 
    "glucose": 131
  }, 
  {
    "trend_arrow": "FLAT", 
    "display_time": "2017-04-03T22:50:39-07:00", 
    "noise": 1, 
    "direction": "Flat", 
    "system_time": "2017-04-04T06:50:35-07:00", 
    "sgv": 130, 
    "dateString": "2017-04-03T22:50:39-07:00", 
    "device": "openaps://indy-ex2/cgm", 
    "unfiltered": 144032, 
    "rssi": 186, 
    "date": 1491285039000.0, 
    "filtered": 140640, 
    "type": "sgv", 
    "glucose": 130
  }
]