[
  {
    "trend_arrow": "FLAT", 
    "display_time": "2017-04-10T05:15:21-07:00", 
    "noise": 1, 
    "direction": "Flat", 
    "system_time": "2017-04-10T13:15:17-07:00", 
    "sgv": 80, 
    "dateString": "2017-04-10T05:15:21-07:00", 
    "device": "openaps://indy-ex2/cgm", 
    "unfiltered": 108944, 
    "rssi": 185, 
    "date": 1491826521000.0, 
    "filtered": 115328, 
    "type": "sgv", 
    "glucose": 80
  }, 
  {
    "trend_arrow": "FLAT", 
    "display_time": "2017-04-10T05:10:21-07:00", 
    "noise": 1, 
    "direction": "Flat", 
    "system_time": "2017-04-10T13:10:17-07:00", 
    "sgv": 85, 
    "dateString": "2017-04-10T05:10:21-07:00", 
    "device": "openaps://indy-ex2/cgm", 
    "unfiltered": 112976, 
    "rssi": 187, 
    "date": 1491826221000.0, 
    "filtered": 119168, 
    "type": "sgv", 
    "glucose": 85
  }, 
  {
    "trend_arrow": "FLAT", 
    "display_time": "2017-04-10T05:05:21-07:00", 
    "noise": 1, 
    "direction": "Flat", 
    "system_time": "2017-04-10T13:05:17-07:00", 
    "sgv": 90, 
    "dateString": "2017-04-10T05:05:21-07:00", 
    "device": "openaps://indy-ex2/cgm", 
    "unfiltered": 117152, 
    "rssi": 185, 
    "date": 1491825921000.0, 
    "filtered": 122768, 
    "type": "sgv", 
    "glucose": 90
  }, 
  {
    "trend_arrow": "FLAT", 
    "display_time": "2017-04-10T05:00:21-07:00", 
    "noise": 1, 
    "direction": "Flat", 
    "system_time": "2017-04-10T13:00:18-07:00", 
    "sgv": 95, 
    "dateString": "2017-04-10T05:00:21-07:00", 
    "device": "openaps://indy-ex2/cgm", 
    "unfiltered": 121136, 
    "rssi": 441, 
    "date": 1491825621000.0, 
    "filtered": 126432, 
    "type": "sgv", 
    "glucose": 95
  }, 
  {
    "trend_arrow": "FLAT", 
    "display_time": "2017-04-10T04:55:21-07:00", 
    "noise": 1, 
    "direction": "Flat", 
    "system_time": "2017-04-10T12:55:17-07:00", 
    "sgv": 99, 
    "dateString": "2017-04-10T04:55:21-07:00", 
    "device": "openaps://indy-ex2/cgm", 
    "unfiltered": 124784, 
    "rssi": 185, 
    "date": 1491825321000.0, 
    "filtered": 130576, 
    "type": "sgv", 
    "glucose": 99
  }, 
  {
    "trend_arrow": "45_DOWN", 
    "display_time": "2017-04-10T04:50:21-07:00", 
    "noise": 1, 
    "direction": "FortyFiveDown", 
    "system_time": "2017-04-10T12:50:17-07:00", 
    "sgv": 103, 
    "dateString": "2017-04-10T04:50:21-07:00", 
    "device": "openaps://indy-ex2/cgm", 
    "unfiltered": 128544, 
    "rssi": 186, 
    "date": 1491825021000.0, 
    "filtered": 135360, 
    "type": "sgv", 
    "glucose": 103
  }
]