[
  {
    "trend_arrow": "FLAT", 
    "system_time": "2017-04-16T04:53:59", 
    "noise": 1, 
    "direction": "Flat", 
    "sgv": 64, 
    "display_time": "2017-04-15T23:04:24", 
    "date": 1492322664000.0, 
    "dateString": "2017-04-15T23:04:24", 
    "unfiltered": 78016, 
    "filtered": 80688, 
    "device": "openaps://indy-ex2/cgm", 
    "rssi": 180, 
    "type": "sgv", 
    "glucose": 64
  }, 
  {
    "trend_arrow": "FLAT", 
    "system_time": "2017-04-16T04:48:59", 
    "noise": 1, 
    "direction": "Flat", 
    "sgv": 65, 
    "display_time": "2017-04-15T22:59:24", 
    "date": 1492322364000.0, 
    "dateString": "2017-04-15T22:59:24", 
    "unfiltered": 79104, 
    "filtered": 81872, 
    "device": "openaps://indy-ex2/cgm", 
    "rssi": 176, 
    "type": "sgv", 
    "glucose": 65
  }, 
  {
    "trend_arrow": "FLAT", 
    "system_time": "2017-04-16T04:43:59", 
    "noise": 1, 
    "direction": "Flat", 
    "sgv": 67, 
    "display_time": "2017-04-15T22:54:24", 
    "date": 1492322064000.0, 
    "dateString": "2017-04-15T22:54:24", 
    "unfiltered": 81168, 
    "filtered": 82432, 
    "device": "openaps://indy-ex2/cgm", 
    "rssi": 180, 
    "type": "sgv", 
    "glucose": 67
  }, 
  {
    "trend_arrow": "FLAT", 
    "system_time": "2017-04-16T04:38:59", 
    "noise": 1, 
    "direction": "Flat", 
    "sgv": 69, 
    "display_time": "2017-04-15T22:49:24", 
    "date": 1492321764000.0, 
    "dateString": "2017-04-15T22:49:24", 
    "unfiltered": 82896, 
    "filtered": 82944, 
    "device": "openaps://indy-ex2/cgm", 
    "rssi": 185, 
    "type": "sgv", 
    "glucose": 69
  }, 
  {
    "trend_arrow": "FLAT", 
    "system_time": "2017-04-16T04:33:59", 
    "noise": 1, 
    "direction": "Flat", 
    "sgv": 70, 
    "display_time": "2017-04-15T22:44:24", 
    "date": 1492321464000.0, 
    "dateString": "2017-04-15T22:44:24", 
    "unfiltered": 83360, 
    "filtered": 84240, 
    "device": "openaps://indy-ex2/cgm", 
    "rssi": 185, 
    "type": "sgv", 
    "glucose": 70
  }, 
  {
    "trend_arrow": "FLAT", 
    "system_time": "2017-04-16T04:28:59", 
    "noise": 1, 
    "direction": "Flat", 
    "sgv": 70, 
    "display_time": "2017-04-15T22:39:24", 
    "date": 1492321164000.0, 
    "dateString": "2017-04-15T22:39:24", 
    "unfiltered": 83440, 
    "filtered": 86448, 
    "device": "openaps://indy-ex2/cgm", 
    "rssi": 181, 
    "type": "sgv", 
    "glucose": 70
  }
]