[
  {
    "trend_arrow": "FLAT", 
    "system_time": "2017-04-21T10:39:12", 
    "noise": 1, 
    "direction": "Flat", 
    "sgv": 192, 
    "display_time": "2017-04-21T02:39:16", 
    "date": 1492767556000.0, 
    "dateString": "2017-04-21T02:39:16", 
    "unfiltered": 181824, 
    "filtered": 178336, 
    "device": "openaps://indy-ex2/cgm", 
    "rssi": 196, 
    "type": "sgv", 
    "glucose": 192
  }, 
  {
    "trend_arrow": "FLAT", 
    "system_time": "2017-04-21T10:34:13", 
    "noise": 1, 
    "direction": "Flat", 
    "sgv": 191, 
    "display_time": "2017-04-21T02:34:16", 
    "date": 1492767256000.0, 
    "dateString": "2017-04-21T02:34:16", 
    "unfiltered": 180832, 
    "filtered": 176352, 
    "device": "openaps://indy-ex2/cgm", 
    "rssi": 185, 
    "type": "sgv", 
    "glucose": 191
  }, 
  {
    "trend_arrow": "FLAT", 
    "system_time": "2017-04-21T10:29:12", 
    "noise": 1, 
    "direction": "Flat", 
    "sgv": 186, 
    "display_time": "2017-04-21T02:29:16", 
    "date": 1492766956000.0, 
    "dateString": "2017-04-21T02:29:16", 
    "unfiltered": 177312, 
    "filtered": 174752, 
    "device": "openaps://indy-ex2/cgm", 
    "rssi": 180, 
    "type": "sgv", 
    "glucose": 186
  }, 
  {
    "trend_arrow": "FLAT", 
    "system_time": "2017-04-21T10:24:12", 
    "noise": 1, 
    "direction": "Flat", 
    "sgv": 183, 
    "display_time": "2017-04-21T02:24:16", 
    "date": 1492766656000.0, 
    "dateString": "2017-04-21T02:24:16", 
    "unfiltered": 174464, 
    "filtered": 173056, 
    "device": "openaps://indy-ex2/cgm", 
    "rssi": 180, 
    "type": "sgv", 
    "glucose": 183
  }, 
  {
    "trend_arrow": "FLAT", 
    "system_time": "2017-04-21T10:19:13", 
    "noise": 1, 
    "direction": "Flat", 
    "sgv": 182, 
    "display_time": "2017-04-21T02:19:17", 
    "date": 1492766357000.0, 
    "dateString": "2017-04-21T02:19:17", 
    "unfiltered": 173696, 
    "filtered": 171168, 
    "device": "openaps://indy-ex2/cgm", 
    "rssi": 438, 
    "type": "sgv", 
    "glucose": 182
  }, 
  {
    "trend_arrow": "FLAT", 
    "system_time": "2017-04-21T10:14:12", 
    "noise": 1, 
    "direction": "Flat", 
    "sgv": 182, 
    "display_time": "2017-04-21T02:14:16", 
    "date": 1492766056000.0, 
    "dateString": "2017-04-21T02:14:16", 
    "unfiltered": 173664, 
    "filtered": 169760, 
    "device": "openaps://indy-ex2/cgm", 
    "rssi": 199, 
    "type": "sgv", 
    "glucose": 182
  }
]