[
  {
    "trend_arrow": "FLAT", 
    "display_time": "2017-03-10T22:46:47-08:00", 
    "noise": 1, 
    "direction": "Flat", 
    "system_time": "2017-03-11T06:45:49-08:00", 
    "sgv": 102, 
    "dateString": "2017-03-10T22:46:47-08:00", 
    "device": "openaps://indy-ex2/cgm", 
    "unfiltered": 108432, 
    "rssi": 440, 
    "date": 1489214807000.0, 
    "filtered": 110352, 
    "type": "sgv", 
    "glucose": 102
  }, 
  {
    "trend_arrow": "FLAT", 
    "display_time": "2017-03-10T22:41:47-08:00", 
    "noise": 1, 
    "direction": "Flat", 
    "system_time": "2017-03-11T06:40:49-08:00", 
    "sgv": 103, 
    "dateString": "2017-03-10T22:41:47-08:00", 
    "device": "openaps://indy-ex2/cgm", 
    "unfiltered": 109360, 
    "rssi": 421, 
    "date": 1489214507000.0, 
    "filtered": 109504, 
    "type": "sgv", 
    "glucose": 103
  }, 
  {
    "trend_arrow": "FLAT", 
    "display_time": "2017-03-10T22:36:47-08:00", 
    "noise": 1, 
    "direction": "Flat", 
    "system_time": "2017-03-11T06:35:49-08:00", 
    "sgv": 103, 
    "dateString": "2017-03-10T22:36:47-08:00", 
    "device": "openaps://indy-ex2/cgm", 
    "unfiltered": 108864, 
    "rssi": 170, 
    "date": 1489214207000.0, 
    "filtered": 106752, 
    "type": "sgv", 
    "glucose": 103
  }, 
  {
    "trend_arrow": "FLAT", 
    "display_time": "2017-03-10T22:31:46-08:00", 
    "noise": 1, 
    "direction": "Flat", 
    "system_time": "2017-03-11T06:30:49-08:00", 
    "sgv": 105, 
    "dateString": "2017-03-10T22:31:46-08:00", 
    "device": "openaps://indy-ex2/cgm", 
    "unfiltered": 110768, 
    "rssi": 204, 
    "date": 1489213906000.0, 
    "filtered": 102816, 
    "type": "sgv", 
    "glucose": 105
  }, 
  {
    "trend_arrow": "FLAT", 
    "display_time": "2017-03-10T22:26:46-08:00", 
    "noise": 1, 
    "direction": "Flat", 
    "system_time": "2017-03-11T06:25:49-08:00", 
    "sgv": 99, 
    "dateString": "2017-03-10T22:26:46-08:00", 
    "device": "openaps://indy-ex2/cgm", 
    "unfiltered": 104960, 
    "rssi": 206, 
    "date": 1489213606000.0, 
    "filtered": 98944, 
    "type": "sgv", 
    "glucose": 99
  }, 
  {
    "trend_arrow": "FLAT", 
    "display_time": "2017-03-10T22:21:46-08:00", 
    "noise": 1, 
    "direction": "Flat", 
    "system_time": "2017-03-11T06:20:49-08:00", 
    "sgv": 94, 
    "dateString": "2017-03-10T22:21:46-08:00", 
    "device": "openaps://indy-ex2/cgm", 
    "unfiltered": 100928, 
    "rssi": 207, 
    "date": 1489213306000.0, 
    "filtered": 96304, 
    "type": "sgv", 
    "glucose": 94
  }
]