[
  {
    "trend_arrow": "FLAT", 
    "display_time": "2017-05-03T05:24:16-07:00", 
    "noise": 1, 
    "system_time": "2017-05-03T13:24:12-07:00", 
    "direction": "Flat", 
    "sgv": 149, 
    "dateString": "2017-05-03T05:24:16-07:00", 
    "device": "openaps://indy-ex2/cgm", 
    "unfiltered": 168192, 
    "rssi": 192, 
    "date": 1493814256000, 
    "filtered": 169536, 
    "type": "sgv", 
    "glucose": 149
  }, 
  {
    "trend_arrow": "FLAT", 
    "display_time": "2017-05-03T05:19:16-07:00", 
    "noise": 1, 
    "system_time": "2017-05-03T13:19:12-07:00", 
    "direction": "Flat", 
    "sgv": 150, 
    "dateString": "2017-05-03T05:19:16-07:00", 
    "device": "openaps://indy-ex2/cgm", 
    "unfiltered": 169056, 
    "rssi": 193, 
    "date": 1493813956000, 
    "filtered": 172416, 
    "type": "sgv", 
    "glucose": 150
  }
]