[
  {
    "trend_arrow": "FLAT", 
    "display_time": "2017-04-28T01:59:26-07:00", 
    "noise": 1, 
    "system_time": "2017-04-28T07:48:44-07:00", 
    "direction": "Flat", 
    "sgv": 202, 
    "dateString": "2017-04-28T01:59:26-07:00", 
    "device": "openaps://indy-ex2/cgm", 
    "unfiltered": 181568, 
    "rssi": 442, 
    "date": 1493369966000, 
    "filtered": 177056, 
    "type": "sgv", 
    "glucose": 202
  }, 
  {
    "trend_arrow": "FLAT", 
    "display_time": "2017-04-28T01:54:25-07:00", 
    "noise": 1, 
    "system_time": "2017-04-28T07:43:44-07:00", 
    "direction": "Flat", 
    "sgv": 196, 
    "dateString": "2017-04-28T01:54:25-07:00", 
    "device": "openaps://indy-ex2/cgm", 
    "unfiltered": 177440, 
    "rssi": 189, 
    "date": 1493369665000, 
    "filtered": 177536, 
    "type": "sgv", 
    "glucose": 196
  }
]